tablericons/__init__.py
tablericons/jinja.py
tablericons/py.typed
tablericons/tablericons.zip
tablericons/templatetags/__init__.py
tablericons/templatetags/tablericons.py
soulclick_tablericons-1.0.0.dist-info/LICENSE
soulclick_tablericons-1.0.0.dist-info/METADATA
soulclick_tablericons-1.0.0.dist-info/WHEEL
soulclick_tablericons-1.0.0.dist-info/top_level.txt
soulclick_tablericons-1.0.0.dist-info/RECORD
