Metadata-Version: 2.1
Name: soulclick-tablericons
Version: 1.0.0
Summary: Use tablericons in your Django and Jinja templates.
Author: Joshua Gartmeier
Project-URL: Changelog, https://github.com/gartmeier/tablericons/blob/main/CHANGELOG.rst
Project-URL: Repository, https://github.com/gartmeier/tablericons
Keywords: Django Jinja
Classifier: Development Status :: 5 - Production/Stable
Classifier: Framework :: Django :: 4.2
Classifier: Framework :: Django :: 5.0
Classifier: Framework :: Django :: 5.1
Classifier: Intended Audience :: Developers
Classifier: License :: OSI Approved :: MIT License
Classifier: Natural Language :: English
Classifier: Operating System :: OS Independent
Classifier: Programming Language :: Python :: 3 :: Only
Classifier: Programming Language :: Python :: 3.9
Classifier: Programming Language :: Python :: 3.10
Classifier: Programming Language :: Python :: 3.11
Classifier: Programming Language :: Python :: 3.12
Classifier: Programming Language :: Python :: 3.13
Classifier: Programming Language :: Python :: Implementation :: CPython
Classifier: Typing :: Typed
Requires-Python: >=3.9
License-File: LICENSE
Provides-Extra: django
Requires-Dist: django>=2.2; extra == "django"
Provides-Extra: jinja
Requires-Dist: jinja2>=2.8; extra == "jinja"
